bioma/__init__.py
bioma/graphs.py
bioma-0.1.0.dist-info/DESCRIPTION.rst
bioma-0.1.0.dist-info/METADATA
bioma-0.1.0.dist-info/RECORD
bioma-0.1.0.dist-info/WHEEL
bioma-0.1.0.dist-info/metadata.json
bioma-0.1.0.dist-info/top_level.txt
